json2tex/__init__.py
json2tex/__main__.py
json2tex/version.py
json2tex-1.3.0.data/data/share/doc/json2tex/README.md
json2tex-1.3.0.data/data/share/doc/json2tex/json2tex.mk
json2tex-1.3.0.dist-info/METADATA
json2tex-1.3.0.dist-info/WHEEL
json2tex-1.3.0.dist-info/entry_points.txt
json2tex-1.3.0.dist-info/top_level.txt
json2tex-1.3.0.dist-info/RECORD
