Metadata-Version: 2.4
Name: json2tex
Version: 1.3.0
Summary: Convert a JSON document to LaTeX commands
Home-page: https://gitlab.com/nobodyinperson/json2tex
Author: Yann Büchau
Author-email: nobodyinperson@posteo.de
License: GPLv3
Keywords: json,latex,tex
Classifier: License :: OSI Approved :: GNU General Public License v3 (GPLv3)
Classifier: Intended Audience :: Science/Research
Requires-Python: >=3.6
Requires-Dist: inflect
Requires-Dist: pylatexenc
Provides-Extra: dev
Requires-Dist: nbstripout; extra == "dev"
Requires-Dist: coverage; extra == "dev"
Requires-Dist: sphinx; extra == "dev"
Requires-Dist: nbsphinx; extra == "dev"
Requires-Dist: sphinx_rtd_theme; extra == "dev"
Requires-Dist: sphinxcontrib-mermaid; extra == "dev"
Requires-Dist: sphinxcontrib.asciinema; extra == "dev"
Requires-Dist: black; extra == "dev"
Requires-Dist: pycodestyle; extra == "dev"
Requires-Dist: setuptools; extra == "dev"
